{"type":"FeatureCollection","features":[{"type":"Feature","geometry":{"type":"Point","coordinates":[79.48751800000008,13.012478000000044]},"properties":{"ps_code":"P12","ps_name":"BANAVARAM","name":"P12 BANAVARAM","dept_code":"","status":true}},{"type":"Feature","geometry":{"type":"Point","coordinates":[79.41700500000007,12.769458000000043]},"properties":{"ps_code":"P16","ps_name":"KALAVAI","name":"P16 KALAVAI","dept_code":"","status":true}},{"type":"Feature","geometry":{"type":"Point","coordinates":[79.45945200000006,12.90080800000004]},"properties":{"ps_code":"P20","ps_name":"KAVERIPAKKAM","name":"P20 KAVERIPAKKAM","dept_code":"","status":true}},{"type":"Feature","geometry":{"type":"Point","coordinates":[79.41957855200008,13.092482567000047]},"properties":{"ps_code":"P21","ps_name":"KONDAPALAYAM","name":"P21 KONDAPALAYAM","dept_code":"","status":true}},{"type":"Feature","geometry":{"type":"Point","coordinates":[79.42104100000006,13.114967000000036]},"properties":{"ps_code":"P38","ps_name":"SHOLINGHUR","name":"P38 SHOLINGHUR","dept_code":"","status":true}},{"type":"Feature","geometry":{"type":"Point","coordinates":[79.61314392100007,12.97348880800007]},"properties":{"ps_code":"P28","ps_name":"NEMILI","name":"P28 NEMILI","dept_code":"","status":true}},{"type":"Feature","geometry":{"type":"Point","coordinates":[79.33031463600008,12.927245140000025]},"properties":{"ps_code":"P35","ps_name":"RANIPET","name":"P35 RANIPET","dept_code":"","status":true}},{"type":"Feature","geometry":{"type":"Point","coordinates":[79.24467468300008,12.940363884000021]},"properties":{"ps_code":"P36","ps_name":"RATHINAGIRI","name":"P36 RATHINAGIRI","dept_code":"","status":true}},{"type":"Feature","geometry":{"type":"Point","coordinates":[79.30524444600007,12.954713821000041]},"properties":{"ps_code":"P39","ps_name":"SIPCOT","name":"P39 SIPCOT","dept_code":"","status":true}},{"type":"Feature","geometry":{"type":"Point","coordinates":[79.71414500000003,13.019467000000077]},"properties":{"ps_code":"P40","ps_name":"THAKKOLAM","name":"P40 THAKKOLAM","dept_code":"","status":true}},{"type":"Feature","geometry":{"type":"Point","coordinates":[79.30682914100004,12.82854406100006]},"properties":{"ps_code":"P41","ps_name":"THIMMIRI","name":"P41 THIMMIRI","dept_code":"","status":true}},{"type":"Feature","geometry":{"type":"Point","coordinates":[79.38644300000004,12.641806000000031]},"properties":{"ps_code":"P46","ps_name":"VALAPANDAL","name":"P46 VALAPANDAL","dept_code":"","status":true}},{"type":"Feature","geometry":{"type":"Point","coordinates":[79.36423167400005,12.925012762000051]},"properties":{"ps_code":"P55","ps_name":"WALAJAH","name":"P55 WALAJAH","dept_code":"","status":true}},{"type":"Feature","geometry":{"type":"Point","coordinates":[79.50620269800004,12.897254944000053]},"properties":{"ps_code":"P56","ps_name":"AVALOOR","name":"P56 AVALOOR","dept_code":"","status":true}},{"type":"Feature","geometry":{"type":"Point","coordinates":[79.65933990500008,13.091486931000077]},"properties":{"ps_code":"P6","ps_name":"ARAKKONAM TALUK","name":"P6 ARAKKONAM TALUK","dept_code":"","status":true}},{"type":"Feature","geometry":{"type":"Point","coordinates":[79.66995239300007,13.083751678000056]},"properties":{"ps_code":"P7","ps_name":"ARAKKONAM TOWN","name":"P7 ARAKKONAM TOWN","dept_code":"","status":true}},{"type":"Feature","geometry":{"type":"Point","coordinates":[79.35153961200007,12.897186279000039]},"properties":{"ps_code":"P8","ps_name":"ARCOT TALUK","name":"P8 ARCOT TALUK","dept_code":"","status":true}},{"type":"Feature","geometry":{"type":"Point","coordinates":[79.32340240500008,12.903223038000021]},"properties":{"ps_code":"P9","ps_name":"ARCOT TOWN","name":"P9 ARCOT TOWN","dept_code":"","status":true}}]}